celery_slack/__init__.py
celery_slack/__version__.py
celery_slack/attachments.py
celery_slack/callbacks.py
celery_slack/exceptions.py
celery_slack/slack.py
celery_slack/slackify.py
celery_slack_webhooks-0.4.6.dist-info/LICENSE.txt
celery_slack_webhooks-0.4.6.dist-info/METADATA
celery_slack_webhooks-0.4.6.dist-info/WHEEL
celery_slack_webhooks-0.4.6.dist-info/top_level.txt
celery_slack_webhooks-0.4.6.dist-info/RECORD
