Metadata-Version: 2.1
Name: celery-slack-webhooks
Version: 0.4.6
Summary: A Slack extension for Celery.
Home-page: https://github.com/leigh-johnson/celery-slack
Author: Leigh Johnson
Author-email: ljohnson@slack-corp.com
License: MIT
Keywords: celery slack
Platform: UNKNOWN
Classifier: Development Status :: 3 - Alpha
Classifier: License :: OSI Approved :: MIT License
Classifier: Natural Language :: English
Classifier: Programming Language :: Python :: 2
Classifier: Programming Language :: Python :: 2.7
Classifier: Programming Language :: Python :: 3
Classifier: Programming Language :: Python :: 3.3
Classifier: Programming Language :: Python :: 3.4
Classifier: Programming Language :: Python :: 3.5
Classifier: Programming Language :: Python :: 3.6
Classifier: Programming Language :: Python :: Implementation :: CPython
Classifier: Topic :: System :: Logging
Classifier: Topic :: System :: Monitoring
Requires-Dist: celery
Requires-Dist: requests
Requires-Dist: ephem
